space_py/__init__.py
rocket_space_stuff-0.1.0.dist-info/METADATA
rocket_space_stuff-0.1.0.dist-info/WHEEL
rocket_space_stuff-0.1.0.dist-info/top_level.txt
rocket_space_stuff-0.1.0.dist-info/RECORD
