Metadata-Version: 2.1
Name: rocket-space-stuff
Version: 0.1.0
Summary: A basic space api
Author: Miro Rava
Author-email: <miro.rava.commercial@gmail.com>
Keywords: python,api,space
Classifier: Development Status :: 4 - Beta
Classifier: Intended Audience :: Developers
Classifier: Programming Language :: Python :: 3
Classifier: Operating System :: Unix
Classifier: Operating System :: MacOS :: MacOS X
Classifier: Operating System :: Microsoft :: Windows
Requires-Dist: requests
